stego_lsb/LSBSteg.py
stego_lsb/StegDetect.py
stego_lsb/WavSteg.py
stego_lsb/__init__.py
stego_lsb/bit_manipulation.py
stego_lsb/cli.py
stego_lsb-1.7.1.dist-info/licenses/AUTHORS.md
stego_lsb-1.7.1.dist-info/licenses/LICENSE.md
stego_lsb-1.7.1.dist-info/METADATA
stego_lsb-1.7.1.dist-info/WHEEL
stego_lsb-1.7.1.dist-info/entry_points.txt
stego_lsb-1.7.1.dist-info/top_level.txt
stego_lsb-1.7.1.dist-info/RECORD
