Metadata-Version: 2.4
Name: stego-lsb
Version: 1.7.1
Summary: Least Significant Bit Steganography for bitmap images (.bmp and .png), WAV sound files, and byte
Author-email: Ryan Gibson <ryan.alex.gibson@gmail.com>
License: MIT
Project-URL: Homepage, https://github.com/ragibson/Steganography
Keywords: steganography,steganalysis
Classifier: Development Status :: 5 - Production/Stable
Classifier: Intended Audience :: Developers
Classifier: Natural Language :: English
Classifier: Programming Language :: Python :: 3
Classifier: Programming Language :: Python :: 3.8
Classifier: Programming Language :: Python :: 3.9
Classifier: Programming Language :: Python :: 3.10
Classifier: Programming Language :: Python :: 3.11
Classifier: Programming Language :: Python :: 3.12
Classifier: Programming Language :: Python :: 3.13
Classifier: Programming Language :: Python :: 3.14
Classifier: Programming Language :: Python :: 3 :: Only
Requires-Python: >=3.8
License-File: LICENSE.md
License-File: AUTHORS.md
Requires-Dist: Click
Requires-Dist: Pillow
Requires-Dist: numpy; python_version >= "3.10"
Requires-Dist: numpy<2.1.0; python_version >= "3.9" and python_version < "3.10"
Requires-Dist: numpy<1.25.0; python_version >= "3.8" and python_version < "3.9"
Dynamic: license-file
